client/__init__.py
client/client.py
client/client/__init__.py
client/client/add_contact.py
client/client/database.py
client/client/del_contact.py
client/client/main_window.py
client/client/main_window_conv.py
client/client/start_dialog.py
client/client/transport.py
client/common/__init__.py
client/common/decos.py
client/common/descripters.py
client/common/errors.py
client/common/metaclasses.py
client/common/params.py
client/common/utils.py
client/logs/__init__.py
client/logs/config_client_log.py
client/logs/config_server_log.py
py_net_chat-0.3.0.dist-info/METADATA
py_net_chat-0.3.0.dist-info/WHEEL
py_net_chat-0.3.0.dist-info/top_level.txt
py_net_chat-0.3.0.dist-info/RECORD
