Metadata-Version: 2.1
Name: py-net-chat
Version: 0.3.0
Summary: NetChat
Home-page: UNKNOWN
Author: NetChatAdmin
Author-email: ncha@yandex.ru
License: UNKNOWN
Platform: UNKNOWN
Requires-Dist: PyQt5
Requires-Dist: sqlalchemy
Requires-Dist: pycryptodome
Requires-Dist: pycryptodomex
